setup.py
athena/__init__.py
athena/backup_grna.py
athena/compile_reactions.py
athena/gillespie_ssa.py
athena/grn.py
athena/grna.py
athena/housekeeping.py
athena/kinetics.py
athena/modular_sampling.py
athena/network.py
athena/sampling.py
athena/signalling_cascade.py
athena/utils.cl
athenasc.egg-info/PKG-INFO
athenasc.egg-info/SOURCES.txt
athenasc.egg-info/dependency_links.txt
athenasc.egg-info/requires.txt
athenasc.egg-info/top_level.txt